{
  "updatedAt": "2026-07-23T07:02:28.265Z",
  "source": "auto",
  "status": "ok",
  "sources": {
    "participation": {
      "label": "Katılım",
      "sourceName": "Dünya Katılım referans kuru",
      "lastSuccessAt": "2026-07-23T07:02:28.265Z",
      "dataStatus": "live",
      "gold": {
        "buy": 6197.64,
        "sell": 6226.93,
        "changePercent": -0.32
      },
      "silver": {
        "buy": 89.65,
        "sell": 90.3,
        "changePercent": -1.06
      }
    },
    "freeMarket": {
      "label": "Serbest Piyasa",
      "sourceName": "Serbest Piyasa referansı",
      "lastSuccessAt": "2026-07-23T07:02:28.265Z",
      "dataStatus": "live",
      "gold": {
        "buy": 6248.14,
        "sell": 6248.96,
        "changePercent": -0.31
      },
      "silver": {
        "buy": 89.9,
        "sell": 90.01,
        "changePercent": -1.07
      }
    }
  }
}
